<?xml version="1.0" encoding="utf-8" standalone="yes"?>
<LinuxDC++>
	<Settings>
		<main-window-maximized type="int">0</main-window-maximized>
		<main-window-pos-x type="int">100</main-window-pos-x>
		<main-window-pos-y type="int">100</main-window-pos-y>
		<main-window-size-x type="int">875</main-window-size-x>
		<main-window-size-y type="int">685</main-window-size-y>
		<nick-pane-position type="int">500</nick-pane-position>
		<notify-download type="int">1</notify-download>
		<notify-pm type="int">1</notify-pm>
		<show-preferences-on-startup type="int">0</show-preferences-on-startup>
		<tab-position type="int">0</tab-position>
		<toolbar-style type="int">5</toolbar-style>
		<transfer-pane-position type="int">455</transfer-pane-position>
		<use-system-icons type="int">0</use-system-icons>
		<default-charset type="string">System default</default-charset>
		<hub-order type="string">0,1,2,3,4,5,6</hub-order>
		<hub-visibility type="string">1,1,1,1,1,1,1</hub-visibility>
		<hub-width type="string">100,75,85,100,85,85,90</hub-width>
		<transfers-order type="string">0,1,2,3,4,5,6,7,8</transfers-order>
		<transfers-visibility type="string">1,1,1,1,1,1,1,1,1</transfers-visibility>
		<transfers-width type="string">150,100,250,90,125,200,125,200,175</transfers-width>
	</Settings>
</LinuxDC++>
